setup.cfg
setup.py
restez/__init__.py
restez/caseless_dict.py
restez/httpconn.py
restez/restez.py
restez/version.py
restez.egg-info/PKG-INFO
restez.egg-info/SOURCES.txt
restez.egg-info/dependency_links.txt
restez.egg-info/entry_points.txt
restez.egg-info/top_level.txt
restez.egg-info/zip-safe