Metadata-Version: 1.0
Name: restez
Version: 0.3.2
Summary: A RESTful HTTP command-line client and library.
Home-page: http://code.google.com/p/restez/
Author: Chris Miles
Author-email: miles.chris@gmail.com
License: MIT
Keywords: REST RESTful HTTP client CLI shell python
Platform: UNKNOWN
